odoo/addons/base_rest_demo/README.rst
odoo/addons/base_rest_demo/__init__.py
odoo/addons/base_rest_demo/__manifest__.py
odoo/addons/base_rest_demo/controllers/__init__.py
odoo/addons/base_rest_demo/controllers/main.py
odoo/addons/base_rest_demo/datamodels/__init__.py
odoo/addons/base_rest_demo/datamodels/country_info.py
odoo/addons/base_rest_demo/datamodels/partner_info.py
odoo/addons/base_rest_demo/datamodels/partner_search_param.py
odoo/addons/base_rest_demo/datamodels/partner_short_info.py
odoo/addons/base_rest_demo/datamodels/state_info.py
odoo/addons/base_rest_demo/i18n/base_rest_demo.pot
odoo/addons/base_rest_demo/i18n/it.po
odoo/addons/base_rest_demo/pydantic_models/__init__.py
odoo/addons/base_rest_demo/pydantic_models/country_info.py
odoo/addons/base_rest_demo/pydantic_models/naive_orm_model.py
odoo/addons/base_rest_demo/pydantic_models/partner_info.py
odoo/addons/base_rest_demo/pydantic_models/partner_search_param.py
odoo/addons/base_rest_demo/pydantic_models/partner_short_info.py
odoo/addons/base_rest_demo/pydantic_models/state_info.py
odoo/addons/base_rest_demo/readme/CONTRIBUTORS.rst
odoo/addons/base_rest_demo/readme/DESCRIPTION.rst
odoo/addons/base_rest_demo/readme/HISTORY.rst
odoo/addons/base_rest_demo/readme/ROADMAP.rst
odoo/addons/base_rest_demo/readme/USAGE.rst
odoo/addons/base_rest_demo/services/__init__.py
odoo/addons/base_rest_demo/services/exception_services.py
odoo/addons/base_rest_demo/services/partner_image_services.py
odoo/addons/base_rest_demo/services/partner_jwt_services.py
odoo/addons/base_rest_demo/services/partner_new_api_services.py
odoo/addons/base_rest_demo/services/partner_pydantic_services.py
odoo/addons/base_rest_demo/services/partner_services.py
odoo/addons/base_rest_demo/services/ping_services.py
odoo/addons/base_rest_demo/static/description/icon.png
odoo/addons/base_rest_demo/static/description/index.html
odoo/addons/base_rest_demo/tests/__init__.py
odoo/addons/base_rest_demo/tests/common.py
odoo_addon_base_rest_demo-16.0.2.0.4.dist-info/METADATA
odoo_addon_base_rest_demo-16.0.2.0.4.dist-info/WHEEL
odoo_addon_base_rest_demo-16.0.2.0.4.dist-info/top_level.txt
odoo_addon_base_rest_demo-16.0.2.0.4.dist-info/RECORD
