Metadata-Version: 2.1
Name: odoo-addon-base_rest_demo
Version: 16.0.2.0.4
Summary: Demo addon for Base REST
Home-page: https://github.com/OCA/rest-framework
Author: ACSONE SA/NV, Odoo Community Association (OCA)
Author-email: support@odoo-community.org
License: LGPL-3
Classifier: Programming Language :: Python
Classifier: Framework :: Odoo
Classifier: Framework :: Odoo :: 16.0
Classifier: License :: OSI Approved :: GNU Lesser General Public License v3 (LGPLv3)
Classifier: Development Status :: 4 - Beta
Requires-Python: >=3.10
Requires-Dist: extendable-pydantic
Requires-Dist: jsondiff
Requires-Dist: marshmallow
Requires-Dist: odoo-addon-base-rest<16.1dev,>=16.0dev
Requires-Dist: odoo-addon-base-rest-datamodel<16.1dev,>=16.0dev
Requires-Dist: odoo-addon-base-rest-pydantic<16.1dev,>=16.0dev
Requires-Dist: odoo-addon-component<16.1dev,>=16.0dev
Requires-Dist: odoo-addon-extendable<16.1dev,>=16.0dev
Requires-Dist: odoo-addon-pydantic<16.1dev,>=16.0dev
Requires-Dist: odoo<16.1dev,>=16.0a
Requires-Dist: pydantic>=2.0.0
